django_mail_viewer/__init__.py
django_mail_viewer/apps.py
django_mail_viewer/models.py
django_mail_viewer/settings.py
django_mail_viewer/urls.py
django_mail_viewer/views.py
django_mail_viewer/backends/__init__.py
django_mail_viewer/backends/cache.py
django_mail_viewer/backends/locmem.py
django_mail_viewer/backends/database/__init__.py
django_mail_viewer/backends/database/admin.py
django_mail_viewer/backends/database/apps.py
django_mail_viewer/backends/database/backend.py
django_mail_viewer/backends/database/models.py
django_mail_viewer/backends/database/migrations/0001_initial.py
django_mail_viewer/backends/database/migrations/__init__.py
django_mail_viewer/static/css/django_mail_viewer.css
django_mail_viewer/static/img/.gitignore
django_mail_viewer/static/js/django_mail_viewer.js
django_mail_viewer/templates/mail_viewer/base.html
django_mail_viewer/templates/mail_viewer/email_delete.html
django_mail_viewer/templates/mail_viewer/email_detail.html
django_mail_viewer/templates/mail_viewer/email_detail_content_fragment.html
django_mail_viewer/templates/mail_viewer/email_list.html
django_mail_viewer/templatetags/__init__.py
django_mail_viewer/templatetags/mail_viewer_tags.py
django_mail_viewer-2.2.0.dist-info/AUTHORS.rst
django_mail_viewer-2.2.0.dist-info/LICENSE
django_mail_viewer-2.2.0.dist-info/METADATA
django_mail_viewer-2.2.0.dist-info/WHEEL
django_mail_viewer-2.2.0.dist-info/top_level.txt
django_mail_viewer-2.2.0.dist-info/RECORD
