Metadata-Version: 2.1
Name: django-mail-viewer
Version: 2.2.0
Summary: View emails in development without actually sending them.
Home-page: https://github.com/jmichalicek/django-mail-viewer
Author: Justin Michalicek
Author-email: jmichalicek@gmail.com
License: MIT
Keywords: django-mail-viewer,django,email
Classifier: Development Status :: 4 - Beta
Classifier: Framework :: Django
Classifier: Framework :: Django :: 3.2
Classifier: Framework :: Django :: 4.0
Classifier: Framework :: Django :: 4.1
Classifier: Intended Audience :: Developers
Classifier: License :: OSI Approved :: MIT License
Classifier: Natural Language :: English
Classifier: Programming Language :: Python :: 3
Classifier: Programming Language :: Python :: 3.7
Classifier: Programming Language :: Python :: 3.8
Classifier: Programming Language :: Python :: 3.9
Classifier: Programming Language :: Python :: 3.10
Classifier: Programming Language :: Python :: 3.11
License-File: LICENSE
License-File: AUTHORS.rst
